ks_utility/./.git
ks_utility/./.gitignore
ks_utility/./LICENSE
ks_utility/./README.en.md
ks_utility/./README.md
ks_utility/./__about__.py
ks_utility/./__init__.py
ks_utility/./aliyuns.py
ks_utility/./arrays.py
ks_utility/./bases.py
ks_utility/./constants.py
ks_utility/./datetimes.py
ks_utility/./dingdings.py
ks_utility/./echarts.py
ks_utility/./encrypts.py
ks_utility/./jsons.py
ks_utility/./lists.py
ks_utility/./logs.py
ks_utility/./maths.py
ks_utility/./numbers.py
ks_utility/./object.py
ks_utility/./pyproject.toml
ks_utility/./requirements.txt
ks_utility/./systems.py
ks_utility/./telegrams.py
ks_utility/./trades.py
ks_utility/./vikas.py.bak
ks_utility/./zmqs.py
ks_utility-0.0.51.dist-info/METADATA
ks_utility-0.0.51.dist-info/WHEEL
ks_utility-0.0.51.dist-info/licenses/LICENSE
ks_utility-0.0.51.dist-info/RECORD
