Metadata-Version: 2.4
Name: ks_utility
Version: 0.0.51
License-Expression: MIT
License-File: LICENSE
Requires-Python: >=3.8
Requires-Dist: alibabacloud-cams20200606>=1.5.0
Requires-Dist: alibabacloud-dysmsapi20170525>=3.0.0
Requires-Dist: cryptography==39.0.2
Requires-Dist: keyring>=25.6.0
Requires-Dist: multitasking==0.0.11
Requires-Dist: pandas>=1.5.3
Requires-Dist: pyecharts==2.0.6
Requires-Dist: python-dateutil==2.9.0
Requires-Dist: pyzmq>=23.2.0
Requires-Dist: sympy>=1.13.0
